README.rst
setup.py
hycl/__init__.py
hycl/core.hy
hycl/nputils.hy
hycl.egg-info/PKG-INFO
hycl.egg-info/SOURCES.txt
hycl.egg-info/dependency_links.txt
hycl.egg-info/requires.txt
hycl.egg-info/top_level.txt