Metadata-Version: 1.1
Name: hycl
Version: 0.0.1.7
Summary: hycl : common-lisp-like functions and macros for hylang
Home-page: https://github.com/riktor/hycl/
Author: Riku Togashi
Author-email: riktor1221@gmail.com
License: MIT License
Keywords: hy lisp common-lisp
Platform: any
Classifier: License :: OSI Approved :: MIT License
Classifier: Operating System :: OS Independent
Classifier: Programming Language :: Python :: 3.4
Classifier: Programming Language :: Python :: 3.5
Classifier: Programming Language :: Python :: 3.6
